{"nodes": [{"id": "volumes_sync_data_tools_tittok_local_extactor_planning_project_md", "label": "PROJECT.md", "file_type": "document", "source_file": ".planning/PROJECT.md", "source_location": "L1"}, {"id": "planning_project_tiktok_extraction_pipeline_project_overview", "label": "TikTok Extraction Pipeline \u2014 Project Overview", "file_type": "document", "source_file": ".planning/PROJECT.md", "source_location": "L1"}, {"id": "planning_project_project_goal", "label": "Project Goal", "file_type": "document", "source_file": ".planning/PROJECT.md", "source_location": "L5"}, {"id": "planning_project_current_milestone_v2_1_compliance_reprocessing", "label": "Current Milestone: v2.1 Compliance & Reprocessing", "file_type": "document", "source_file": ".planning/PROJECT.md", "source_location": "L9"}, {"id": "planning_project_milestone_progress", "label": "Milestone Progress", "file_type": "document", "source_file": ".planning/PROJECT.md", "source_location": "L15"}, {"id": "planning_project_core_value", "label": "Core Value", "file_type": "document", "source_file": ".planning/PROJECT.md", "source_location": "L26"}, {"id": "planning_project_key_constraints", "label": "Key Constraints", "file_type": "document", "source_file": ".planning/PROJECT.md", "source_location": "L30"}, {"id": "planning_project_out_of_scope", "label": "Out of Scope", "file_type": "document", "source_file": ".planning/PROJECT.md", "source_location": "L39"}, {"id": "planning_project_context", "label": "Context", "file_type": "document", "source_file": ".planning/PROJECT.md", "source_location": "L44"}, {"id": "planning_project_constraints", "label": "Constraints", "file_type": "document", "source_file": ".planning/PROJECT.md", "source_location": "L50"}, {"id": "planning_project_key_decisions", "label": "Key Decisions", "file_type": "document", "source_file": ".planning/PROJECT.md", "source_location": "L56"}, {"id": "planning_project_evolution", "label": "Evolution", "file_type": "document", "source_file": ".planning/PROJECT.md", "source_location": "L62"}, {"id": "planning_project_last_updated", "label": "Last updated", "file_type": "document", "source_file": ".planning/PROJECT.md", "source_location": "L81"}], "edges": [{"source": "volumes_sync_data_tools_tittok_local_extactor_planning_project_md", "target": "planning_project_tiktok_extraction_pipeline_project_overview", "relation": "contains", "confidence": "EXTRACTED", "source_file": ".planning/PROJECT.md", "source_location": "L1", "weight": 1.0}, {"source": "planning_project_tiktok_extraction_pipeline_project_overview", "target": "planning_project_project_goal", "relation": "contains", "confidence": "EXTRACTED", "source_file": ".planning/PROJECT.md", "source_location": "L5", "weight": 1.0}, {"source": "planning_project_tiktok_extraction_pipeline_project_overview", "target": "planning_project_current_milestone_v2_1_compliance_reprocessing", "relation": "contains", "confidence": "EXTRACTED", "source_file": ".planning/PROJECT.md", "source_location": "L9", "weight": 1.0}, {"source": "planning_project_current_milestone_v2_1_compliance_reprocessing", "target": "planning_project_milestone_progress", "relation": "contains", "confidence": "EXTRACTED", "source_file": ".planning/PROJECT.md", "source_location": "L15", "weight": 1.0}, {"source": "planning_project_tiktok_extraction_pipeline_project_overview", "target": "planning_project_core_value", "relation": "contains", "confidence": "EXTRACTED", "source_file": ".planning/PROJECT.md", "source_location": "L26", "weight": 1.0}, {"source": "planning_project_tiktok_extraction_pipeline_project_overview", "target": "planning_project_key_constraints", "relation": "contains", "confidence": "EXTRACTED", "source_file": ".planning/PROJECT.md", "source_location": "L30", "weight": 1.0}, {"source": "planning_project_key_constraints", "target": "planning_project_out_of_scope", "relation": "contains", "confidence": "EXTRACTED", "source_file": ".planning/PROJECT.md", "source_location": "L39", "weight": 1.0}, {"source": "planning_project_tiktok_extraction_pipeline_project_overview", "target": "planning_project_context", "relation": "contains", "confidence": "EXTRACTED", "source_file": ".planning/PROJECT.md", "source_location": "L44", "weight": 1.0}, {"source": "planning_project_tiktok_extraction_pipeline_project_overview", "target": "planning_project_constraints", "relation": "contains", "confidence": "EXTRACTED", "source_file": ".planning/PROJECT.md", "source_location": "L50", "weight": 1.0}, {"source": "planning_project_tiktok_extraction_pipeline_project_overview", "target": "planning_project_key_decisions", "relation": "contains", "confidence": "EXTRACTED", "source_file": ".planning/PROJECT.md", "source_location": "L56", "weight": 1.0}, {"source": "planning_project_tiktok_extraction_pipeline_project_overview", "target": "planning_project_evolution", "relation": "contains", "confidence": "EXTRACTED", "source_file": ".planning/PROJECT.md", "source_location": "L62", "weight": 1.0}, {"source": "planning_project_tiktok_extraction_pipeline_project_overview", "target": "planning_project_last_updated", "relation": "contains", "confidence": "EXTRACTED", "source_file": ".planning/PROJECT.md", "source_location": "L81", "weight": 1.0}], "input_tokens": 0, "output_tokens": 0}